{
  "actions_summary": [
    {
      "can_act": false,
      "count": 0,
      "hidden": false,
      "id": 4
    },
    {
      "can_act": false,
      "count": 0,
      "hidden": false,
      "id": 8
    },
    {
      "can_act": false,
      "count": 0,
      "hidden": false,
      "id": 10
    },
    {
      "can_act": false,
      "count": 0,
      "hidden": false,
      "id": 7
    }
  ],
  "archetype": "regular",
  "archived": false,
  "bookmarked": false,
  "bookmarks": [],
  "can_vote": false,
  "category_id": 163,
  "chunk_size": 20,
  "closed": false,
  "created_at": "2025-03-20T15:02:02.242Z",
  "current_post_number": 1,
  "deleted_at": null,
  "deleted_by": null,
  "details": {
    "can_edit": false,
    "created_by": {
      "avatar_template": "/user_avatar/forum.bambulab.com/lilac_rage/{size}/17017_2.png",
      "id": 17216,
      "name": "Lilac Rage",
      "username": "Lilac_Rage"
    },
    "last_poster": {
      "avatar_template": "/user_avatar/forum.bambulab.com/lilac_rage/{size}/17017_2.png",
      "id": 17216,
      "name": "Lilac Rage",
      "username": "Lilac_Rage"
    },
    "links": [
      {
        "attachment": false,
        "clicks": 1,
        "domain": "en.wikipedia.org",
        "internal": false,
        "reflection": false,
        "root_domain": "wikipedia.org",
        "title": "TrueType - Wikipedia",
        "url": "https://en.wikipedia.org/wiki/TrueType",
        "user_id": 17216
      }
    ],
    "notification_level": 1,
    "participants": [
      {
        "avatar_template": "/user_avatar/forum.bambulab.com/lilac_rage/{size}/17017_2.png",
        "flair_bg_color": null,
        "flair_color": null,
        "flair_group_id": null,
        "flair_name": null,
        "flair_url": null,
        "id": 17216,
        "name": "Lilac Rage",
        "post_count": 3,
        "primary_group_name": null,
        "trust_level": 2,
        "username": "Lilac_Rage"
      },
      {
        "avatar_template": "/user_avatar/forum.bambulab.com/rocketsled/{size}/10549_2.png",
        "flair_bg_color": null,
        "flair_color": null,
        "flair_group_id": null,
        "flair_name": null,
        "flair_url": null,
        "id": 7720,
        "name": "Randy Cohen",
        "post_count": 1,
        "primary_group_name": null,
        "trust_level": 2,
        "username": "RocketSled"
      }
    ]
  },
  "discourse_zendesk_plugin_zendesk_id": null,
  "discourse_zendesk_plugin_zendesk_url": "https://your-url.zendesk.com/agent/tickets/",
  "draft": null,
  "draft_key": "topic_154198",
  "draft_sequence": null,
  "fancy_title": "Request: Parametric Model Maker - Upload Custom Fonts",
  "featured_link": null,
  "has_summary": false,
  "highest_post_number": 4,
  "id": 154198,
  "image_url": null,
  "last_posted_at": "2025-03-20T19:00:05.821Z",
  "like_count": 10,
  "message_bus_last_id": 0,
  "participant_count": 2,
  "pinned": false,
  "pinned_at": null,
  "pinned_globally": false,
  "pinned_until": null,
  "post_stream": {
    "posts": [
      {
        "accepted_answer": false,
        "actions_summary": [
          {
            "count": 4,
            "id": 2
          }
        ],
        "admin": false,
        "avatar_template": "/user_avatar/forum.bambulab.com/lilac_rage/{size}/17017_2.png",
        "badges_granted": [],
        "bookmarked": false,
        "can_accept_answer": false,
        "can_delete": false,
        "can_edit": false,
        "can_recover": false,
        "can_see_hidden_post": false,
        "can_unaccept_answer": false,
        "can_view_edit_history": true,
        "can_vote": false,
        "can_wiki": false,
        "cooked": "<p>PARAMETRIC MODEL MAKER feature request:</p>\n<p>As we now have the ability to upload files in a somewhat limited capacity (PNG, SVG, STL) I want to suggest adding the ability to upload custom font files (.TTF, .OTF).</p>\n<p>Openscad has a fairly robust text feature set, and being able to use custom fonts would really, really open up the possibilities here.</p>",
        "created_at": "2025-03-20T15:02:02.356Z",
        "current_user_reaction": null,
        "current_user_used_main_reaction": false,
        "deleted_at": null,
        "display_username": "Lilac Rage",
        "edit_reason": null,
        "flair_bg_color": null,
        "flair_color": null,
        "flair_group_id": null,
        "flair_name": null,
        "flair_url": null,
        "hidden": false,
        "id": 411635,
        "incoming_link_count": 295,
        "moderator": false,
        "name": "Lilac Rage",
        "post_number": 1,
        "post_type": 1,
        "post_url": "/t/request-parametric-model-maker-upload-custom-fonts/154198/1",
        "posts_count": 4,
        "primary_group_name": null,
        "quote_count": 0,
        "reaction_users_count": 4,
        "reactions": [
          {
            "count": 4,
            "id": "+1",
            "type": "emoji"
          }
        ],
        "read": true,
        "readers_count": 48,
        "reads": 49,
        "reply_count": 0,
        "reply_to_post_number": null,
        "score": 1534.8,
        "staff": false,
        "topic_accepted_answer": null,
        "topic_id": 154198,
        "topic_slug": "request-parametric-model-maker-upload-custom-fonts",
        "trust_level": 2,
        "updated_at": "2025-05-01T16:18:40.265Z",
        "user_deleted": false,
        "user_id": 17216,
        "user_title": null,
        "username": "Lilac_Rage",
        "version": 3,
        "wiki": false,
        "yours": false
      },
      {
        "accepted_answer": false,
        "actions_summary": [
          {
            "count": 2,
            "id": 2
          }
        ],
        "admin": false,
        "avatar_template": "/user_avatar/forum.bambulab.com/rocketsled/{size}/10549_2.png",
        "badges_granted": [],
        "bookmarked": false,
        "can_accept_answer": false,
        "can_delete": false,
        "can_edit": false,
        "can_recover": false,
        "can_see_hidden_post": false,
        "can_unaccept_answer": false,
        "can_view_edit_history": true,
        "can_wiki": false,
        "cooked": "<p>But a Slicer isn\u2019t a CAD program. So this is a specious comparison.</p>\n<p>You can probably use any font you want in any CAD program you use. I do. If you don\u2019t know how to use CAD software, it\u2019s something worth learning so that you aren\u2019t constrained by the limitations of the slicer\u2026</p>",
        "created_at": "2025-03-20T15:20:57.183Z",
        "current_user_reaction": null,
        "current_user_used_main_reaction": false,
        "deleted_at": null,
        "display_username": "Randy Cohen",
        "edit_reason": null,
        "flair_bg_color": null,
        "flair_color": null,
        "flair_group_id": null,
        "flair_name": null,
        "flair_url": null,
        "hidden": false,
        "id": 411652,
        "incoming_link_count": 0,
        "moderator": false,
        "name": "Randy Cohen",
        "post_number": 2,
        "post_type": 1,
        "post_url": "/t/request-parametric-model-maker-upload-custom-fonts/154198/2",
        "posts_count": 4,
        "primary_group_name": null,
        "quote_count": 0,
        "reaction_users_count": 2,
        "reactions": [
          {
            "count": 1,
            "id": "+1",
            "type": "emoji"
          },
          {
            "count": 1,
            "id": "-1",
            "type": "emoji"
          }
        ],
        "read": true,
        "readers_count": 48,
        "reads": 49,
        "reply_count": 1,
        "reply_to_post_number": null,
        "score": 74.8,
        "staff": false,
        "topic_accepted_answer": null,
        "topic_id": 154198,
        "topic_slug": "request-parametric-model-maker-upload-custom-fonts",
        "trust_level": 2,
        "updated_at": "2025-03-20T15:20:57.183Z",
        "user_deleted": false,
        "user_id": 7720,
        "user_title": null,
        "username": "RocketSled",
        "version": 1,
        "wiki": false,
        "yours": false
      },
      {
        "accepted_answer": false,
        "actions_summary": [],
        "admin": false,
        "avatar_template": "/user_avatar/forum.bambulab.com/lilac_rage/{size}/17017_2.png",
        "badges_granted": [],
        "bookmarked": false,
        "can_accept_answer": false,
        "can_delete": false,
        "can_edit": false,
        "can_recover": false,
        "can_see_hidden_post": false,
        "can_unaccept_answer": false,
        "can_view_edit_history": true,
        "can_wiki": false,
        "cooked": "<p>I\u2019m talking about the parametric model maker, not bambu studio</p>",
        "created_at": "2025-03-20T15:31:52.718Z",
        "current_user_reaction": null,
        "current_user_used_main_reaction": false,
        "deleted_at": null,
        "display_username": "Lilac Rage",
        "edit_reason": null,
        "flair_bg_color": null,
        "flair_color": null,
        "flair_group_id": null,
        "flair_name": null,
        "flair_url": null,
        "hidden": false,
        "id": 411667,
        "incoming_link_count": 0,
        "moderator": false,
        "name": "Lilac Rage",
        "post_number": 3,
        "post_type": 1,
        "post_url": "/t/request-parametric-model-maker-upload-custom-fonts/154198/3",
        "posts_count": 4,
        "primary_group_name": null,
        "quote_count": 0,
        "reaction_users_count": 0,
        "reactions": [],
        "read": true,
        "readers_count": 46,
        "reads": 47,
        "reply_count": 0,
        "reply_to_post_number": 2,
        "reply_to_user": {
          "avatar_template": "/user_avatar/forum.bambulab.com/rocketsled/{size}/10549_2.png",
          "id": 7720,
          "name": "Randy Cohen",
          "username": "RocketSled"
        },
        "score": 9.4,
        "staff": false,
        "topic_accepted_answer": null,
        "topic_id": 154198,
        "topic_slug": "request-parametric-model-maker-upload-custom-fonts",
        "trust_level": 2,
        "updated_at": "2025-03-20T15:31:52.718Z",
        "user_deleted": false,
        "user_id": 17216,
        "user_title": null,
        "username": "Lilac_Rage",
        "version": 1,
        "wiki": false,
        "yours": false
      },
      {
        "accepted_answer": false,
        "actions_summary": [
          {
            "count": 4,
            "id": 2
          }
        ],
        "admin": false,
        "avatar_template": "/user_avatar/forum.bambulab.com/lilac_rage/{size}/17017_2.png",
        "badges_granted": [],
        "bookmarked": false,
        "can_accept_answer": false,
        "can_delete": false,
        "can_edit": false,
        "can_recover": false,
        "can_see_hidden_post": false,
        "can_unaccept_answer": false,
        "can_view_edit_history": true,
        "can_wiki": false,
        "cooked": "<p>To be clear, this is also supported in OpenSCAD.</p>\n<blockquote>\n<p>In addition to the installed fonts ( for windows only fonts installed as admin for all users ), it\u2019s possible to add project specific font files. Supported font file formats are <a href=\"https://en.wikipedia.org/wiki/TrueType\" rel=\"noopener nofollow ugc\">TrueType</a> Fonts (<em>.ttf) and <a href=\"https://en.wikipedia.org/wiki/OpenType\" rel=\"noopener nofollow ugc\">OpenType</a> Fonts (</em>.otf). The files need to be registered with use&lt;&gt;.</p>\n</blockquote>\n<pre><code class=\"lang-auto\"> use &lt;ttf/paratype-serif/PTF55F.ttf&gt;\n</code></pre>\n<p>It seems relatively simple to expand the allowed uploaded files to include <code>.ttf</code> and <code>.otf</code> file types, which would allow developers (and users) to add custom fonts for their parametric models.</p>",
        "created_at": "2025-03-20T19:00:05.821Z",
        "current_user_reaction": null,
        "current_user_used_main_reaction": false,
        "deleted_at": null,
        "display_username": "Lilac Rage",
        "edit_reason": null,
        "flair_bg_color": null,
        "flair_color": null,
        "flair_group_id": null,
        "flair_name": null,
        "flair_url": null,
        "hidden": false,
        "id": 411993,
        "incoming_link_count": 3,
        "link_counts": [
          {
            "clicks": 1,
            "internal": false,
            "reflection": false,
            "title": "TrueType - Wikipedia",
            "url": "https://en.wikipedia.org/wiki/TrueType"
          },
          {
            "clicks": 0,
            "internal": false,
            "reflection": false,
            "title": "OpenType - Wikipedia",
            "url": "https://en.wikipedia.org/wiki/OpenType"
          }
        ],
        "moderator": false,
        "name": "Lilac Rage",
        "post_number": 4,
        "post_type": 1,
        "post_url": "/t/request-parametric-model-maker-upload-custom-fonts/154198/4",
        "posts_count": 4,
        "primary_group_name": null,
        "quote_count": 0,
        "reaction_users_count": 4,
        "reactions": [
          {
            "count": 4,
            "id": "+1",
            "type": "emoji"
          }
        ],
        "read": true,
        "readers_count": 39,
        "reads": 40,
        "reply_count": 0,
        "reply_to_post_number": null,
        "score": 83.0,
        "staff": false,
        "topic_accepted_answer": null,
        "topic_id": 154198,
        "topic_slug": "request-parametric-model-maker-upload-custom-fonts",
        "trust_level": 2,
        "updated_at": "2025-03-20T19:00:05.821Z",
        "user_deleted": false,
        "user_id": 17216,
        "user_title": null,
        "username": "Lilac_Rage",
        "version": 1,
        "wiki": false,
        "yours": false
      }
    ],
    "stream": [
      411635,
      411652,
      411667,
      411993
    ]
  },
  "posts_count": 4,
  "reply_count": 1,
  "show_read_indicator": false,
  "slow_mode_enabled_until": null,
  "slow_mode_seconds": 0,
  "slug": "request-parametric-model-maker-upload-custom-fonts",
  "suggested_topics": [
    {
      "archetype": "regular",
      "archived": false,
      "bookmarked": null,
      "bumped": true,
      "bumped_at": "2026-01-23T19:41:35.908Z",
      "category_id": 163,
      "closed": false,
      "created_at": "2026-01-23T15:22:48.534Z",
      "fancy_title": "Lightbox issue gaps after vectorising image",
      "featured_link": null,
      "has_accepted_answer": false,
      "highest_post_number": 5,
      "id": 227585,
      "image_url": "https://cdn-forum.bambulab.com/original/3X/c/3/c3aa4f3ee5416bea816ecbb9877963576cf20150.jpeg",
      "last_posted_at": "2026-01-23T19:41:35.908Z",
      "like_count": 0,
      "liked": null,
      "op_like_count": 0,
      "pinned": false,
      "posters": [
        {
          "description": "Original Poster, Most Recent Poster",
          "extras": "latest",
          "user": {
            "avatar_template": "/user_avatar/forum.bambulab.com/w177/{size}/101858_2.png",
            "id": 138049,
            "name": "W177",
            "trust_level": 1,
            "username": "w177"
          }
        },
        {
          "description": "Frequent Poster",
          "extras": null,
          "user": {
            "avatar_template": "/user_avatar/forum.bambulab.com/waynejohns1973/{size}/125383_2.png",
            "id": 23549,
            "name": "W3DPT",
            "trust_level": 2,
            "username": "waynejohns1973"
          }
        },
        {
          "description": "Frequent Poster",
          "extras": null,
          "user": {
            "avatar_template": "/user_avatar/forum.bambulab.com/mzip/{size}/76349_2.png",
            "id": 23328,
            "name": "Yabba Dabba Doo!",
            "trust_level": 2,
            "username": "MZip"
          }
        }
      ],
      "posts_count": 5,
      "reply_count": 3,
      "slug": "lightbox-issue-gaps-after-vectorising-image",
      "tags": [],
      "tags_descriptions": {},
      "title": "Lightbox issue gaps after vectorising image",
      "unpinned": null,
      "unseen": false,
      "views": 202,
      "visible": true
    },
    {
      "archetype": "regular",
      "archived": false,
      "bookmarked": null,
      "bumped": true,
      "bumped_at": "2025-07-09T17:05:33.080Z",
      "category_id": 163,
      "closed": false,
      "created_at": "2025-07-09T17:05:33.017Z",
      "fancy_title": "Parametric Model Maker: Edit 3MF Customizer -&gt; Detect thin walls",
      "featured_link": null,
      "has_accepted_answer": false,
      "highest_post_number": 1,
      "id": 181316,
      "image_url": null,
      "last_posted_at": "2025-07-09T17:05:33.080Z",
      "like_count": 0,
      "liked": null,
      "op_like_count": 0,
      "pinned": false,
      "posters": [
        {
          "description": "Original Poster, Most Recent Poster",
          "extras": "latest single",
          "user": {
            "avatar_template": "/user_avatar/forum.bambulab.com/jetpad/{size}/32448_2.png",
            "id": 29303,
            "name": "jetpad",
            "trust_level": 2,
            "username": "jetpad"
          }
        }
      ],
      "posts_count": 1,
      "reply_count": 0,
      "slug": "parametric-model-maker-edit-3mf-customizer-detect-thin-walls",
      "tags": [],
      "tags_descriptions": {},
      "title": "Parametric Model Maker: Edit 3MF Customizer -> Detect thin walls",
      "unpinned": null,
      "unseen": false,
      "views": 83,
      "visible": true
    },
    {
      "archetype": "regular",
      "archived": false,
      "bookmarked": null,
      "bumped": true,
      "bumped_at": "2025-05-15T09:38:38.679Z",
      "category_id": 163,
      "closed": false,
      "created_at": "2025-05-15T09:38:38.624Z",
      "fancy_title": "Lightbox Maker, the frame",
      "featured_link": null,
      "has_accepted_answer": false,
      "highest_post_number": 1,
      "id": 169451,
      "image_url": null,
      "last_posted_at": "2025-05-15T09:38:38.679Z",
      "like_count": 3,
      "liked": null,
      "op_like_count": 3,
      "pinned": false,
      "posters": [
        {
          "description": "Original Poster, Most Recent Poster",
          "extras": "latest single",
          "user": {
            "avatar_template": "/user_avatar/forum.bambulab.com/mwiman/{size}/13500_2.png",
            "id": 61082,
            "name": "Mats Wiman",
            "trust_level": 1,
            "username": "MWiman"
          }
        }
      ],
      "posts_count": 1,
      "reply_count": 0,
      "slug": "lightbox-maker-the-frame",
      "tags": [],
      "tags_descriptions": {},
      "title": "Lightbox Maker, the frame",
      "unpinned": null,
      "unseen": false,
      "views": 191,
      "visible": true
    },
    {
      "archetype": "regular",
      "archived": false,
      "bookmarked": null,
      "bumped": true,
      "bumped_at": "2025-04-22T14:15:00.071Z",
      "category_id": 163,
      "closed": false,
      "created_at": "2025-04-22T14:14:59.960Z",
      "fancy_title": "Make my statue hits bambu handy",
      "featured_link": null,
      "has_accepted_answer": false,
      "highest_post_number": 1,
      "id": 163517,
      "image_url": "https://cdn-forum.bambulab.com/optimized/3X/c/3/c30d779d881689fd308ef239012534b8cec36855_2_1024x635.jpeg",
      "last_posted_at": "2025-04-22T14:15:00.071Z",
      "like_count": 0,
      "liked": null,
      "op_like_count": 0,
      "pinned": false,
      "posters": [
        {
          "description": "Original Poster, Most Recent Poster",
          "extras": "latest single",
          "user": {
            "avatar_template": "/user_avatar/forum.bambulab.com/neiljt/{size}/108134_2.png",
            "id": 27503,
            "name": "Neiljt",
            "trust_level": 2,
            "username": "Neiljt"
          }
        }
      ],
      "posts_count": 1,
      "reply_count": 0,
      "slug": "make-my-statue-hits-bambu-handy",
      "tags": [],
      "tags_descriptions": {},
      "title": "Make my statue hits bambu handy",
      "unpinned": null,
      "unseen": false,
      "views": 216,
      "visible": true
    },
    {
      "archetype": "regular",
      "archived": false,
      "bookmarked": null,
      "bumped": true,
      "bumped_at": "2026-03-15T14:25:55.519Z",
      "category_id": 163,
      "closed": false,
      "created_at": "2026-03-14T13:56:39.364Z",
      "fancy_title": "Color Support for Model Maker not working properly in Bambu Studio",
      "featured_link": null,
      "has_accepted_answer": false,
      "highest_post_number": 4,
      "id": 241443,
      "image_url": "https://cdn-forum.bambulab.com/optimized/3X/0/2/02857a2e16a42df76768ef2f9e67fbf382143fba_2_1024x555.png",
      "last_posted_at": "2026-03-15T14:25:55.519Z",
      "like_count": 1,
      "liked": null,
      "op_like_count": 0,
      "pinned": false,
      "posters": [
        {
          "description": "Original Poster, Most Recent Poster",
          "extras": "latest",
          "user": {
            "avatar_template": "/user_avatar/forum.bambulab.com/neofabric/{size}/145507_2.png",
            "id": 143648,
            "name": "Neofabric",
            "trust_level": 2,
            "username": "NEOFABRIC"
          }
        },
        {
          "description": "Frequent Poster",
          "extras": null,
          "user": {
            "avatar_template": "/user_avatar/forum.bambulab.com/malctheoracle/{size}/137308_2.png",
            "id": 37295,
            "name": "Every tool has its hidden purpose.",
            "trust_level": 2,
            "username": "MalcTheOracle"
          }
        }
      ],
      "posts_count": 4,
      "reply_count": 2,
      "slug": "color-support-for-model-maker-not-working-properly-in-bambu-studio",
      "tags": [],
      "tags_descriptions": {},
      "title": "Color Support for Model Maker not working properly in Bambu Studio",
      "unpinned": null,
      "unseen": false,
      "views": 96,
      "visible": true
    }
  ],
  "tags": [
    "product-request"
  ],
  "tags_descriptions": {},
  "thumbnails": null,
  "timeline_lookup": [
    [
      1,
      397
    ]
  ],
  "title": "Request: Parametric Model Maker - Upload Custom Fonts",
  "topic_timer": null,
  "unpinned": null,
  "user_id": 17216,
  "user_voted": false,
  "valid_reactions": [
    "+1",
    "-1",
    "heart",
    "100",
    "laughing",
    "open_mouth",
    "clap"
  ],
  "views": 350,
  "visible": true,
  "vote_count": 0,
  "word_count": 230
}
